smqtk_descriptors/__init__.py
smqtk_descriptors/descriptor_element_factory.py
smqtk_descriptors/impls/__init__.py
smqtk_descriptors/impls/descriptor_element/__init__.py
smqtk_descriptors/impls/descriptor_element/file.py
smqtk_descriptors/impls/descriptor_element/memory.py
smqtk_descriptors/impls/descriptor_element/postgres.py
smqtk_descriptors/impls/descriptor_element/solr.py
smqtk_descriptors/impls/descriptor_generator/__init__.py
smqtk_descriptors/impls/descriptor_generator/caffe1.py
smqtk_descriptors/impls/descriptor_generator/image_descriptor_generator_wrapper.py
smqtk_descriptors/impls/descriptor_generator/prepopulated.py
smqtk_descriptors/impls/descriptor_generator/pytorch.py
smqtk_descriptors/impls/descriptor_set/__init__.py
smqtk_descriptors/impls/descriptor_set/memory.py
smqtk_descriptors/impls/descriptor_set/postgres.py
smqtk_descriptors/impls/descriptor_set/solr.py
smqtk_descriptors/interfaces/__init__.py
smqtk_descriptors/interfaces/descriptor_element.py
smqtk_descriptors/interfaces/descriptor_generator.py
smqtk_descriptors/interfaces/descriptor_set.py
smqtk_descriptors/interfaces/image_descriptor_generator.py
smqtk_descriptors/py.typed
smqtk_descriptors/utils/__init__.py
smqtk_descriptors/utils/parallel.py
smqtk_descriptors/utils/pytorch_utils.py
smqtk_descriptors-0.20.0.dist-info/LICENSE.txt
smqtk_descriptors-0.20.0.dist-info/METADATA
smqtk_descriptors-0.20.0.dist-info/WHEEL
smqtk_descriptors-0.20.0.dist-info/entry_points.txt
smqtk_descriptors-0.20.0.dist-info/RECORD
