Metadata-Version: 2.1
Name: smqtk_descriptors
Version: 0.20.0
Summary: Algorithms, data structures and utilities around computingdescriptor vectors from data.
Home-page: https://github.com/Kitware/SMQTK-Descriptors
License: BSD-3-Clause
Author: Kitware, Inc.
Author-email: smqtk-developers@kitware.com
Requires-Python: >=3.10,<4.0
Classifier: Development Status :: 3 - Alpha
Classifier: Intended Audience :: Developers
Classifier: Intended Audience :: Science/Research
Classifier: License :: OSI Approved :: BSD License
Classifier: Operating System :: MacOS :: MacOS X
Classifier: Operating System :: Unix
Classifier: Programming Language :: Python :: 3
Classifier: Programming Language :: Python :: 3.10
Classifier: Programming Language :: Python :: 3.11
Classifier: Programming Language :: Python :: 3.12
Classifier: Programming Language :: Python :: 3.13
Provides-Extra: pytorch
Requires-Dist: numpy (>=1.19.5)
Requires-Dist: smqtk-core (>=0.20.0)
Requires-Dist: smqtk-dataprovider (>=0.19.0)
Requires-Dist: smqtk-image-io (>=0.18.0)
Requires-Dist: torch (>=1.10.0,!=2.0.1) ; extra == "pytorch"
Requires-Dist: torchvision (>=0.11.1) ; extra == "pytorch"
Project-URL: Documentation, https://smqtk-descriptors.readthedocs.io/
Project-URL: Repository, https://github.com/Kitware/SMQTK-Descriptors
